{
  "source": "https://canlidoviz.com/altin-fiyatlari/",
  "last_update": "2026-01-28T23:53:50.868355Z",
  "count": 8,
  "items": [
    {
      "raw": [
        "Dolar",
        "43.4346%0.07"
      ]
    },
    {
      "raw": [
        "Euro",
        "52.1168%0.45"
      ]
    },
    {
      "raw": [
        "Gram Altın",
        "7726.54%2.81"
      ]
    },
    {
      "raw": [
        "İngiliz Sterlini",
        "60.3875%0.22"
      ]
    },
    {
      "raw": [
        "Euro Dolar",
        "1.1973%0.22"
      ]
    },
    {
      "raw": [
        "ONS Altın",
        "5500.50%2.28"
      ]
    },
    {
      "raw": [
        "Gümüş",
        "165.9918%1.75"
      ]
    },
    {
      "raw": [
        "Altın Gümüş",
        "46.8200%1.39"
      ]
    }
  ]
}